cary_reader/__init__.py
cary_reader/cary_data.py
cary_reader-0.3.dist-info/LICENSE.md
cary_reader-0.3.dist-info/METADATA
cary_reader-0.3.dist-info/WHEEL
cary_reader-0.3.dist-info/top_level.txt
cary_reader-0.3.dist-info/RECORD
